[
  {
    "poolNumber": "39",
    "protocolName": "TraderJoe",
    "contract": "0xd6a4F121CA35509aF06A0Be99093d08462f53052",
    "symbol0Name": "USDC.e",
    "symbol1Name": "WAVAX",
    "symbol0address": "0xa7d7079b0fead91f3e65f86e8915cb59c1a4c664",
    "symbol0price": "1.0000000000000000",
    "symbol1address": "0xb31f66aa3c1e785363f0875a1b74e27b85fd66c7",
    "symbol1price": "81.4642480000000000",
    "network": "avaxc",
    "lpAddress": "0xa389f9430876455c36478deea9769b7ca4e3ddb1",
    "coinsASec": 0.584375,
    "tvl": 219325000,
    "apy": "10.438664476114",
    "apyDaily": 0.028599080756476714,
    "apyMonthly": 0.8698887063428334,
    "totalApy": 10.438664476114,
    "totalApyDaily": 0.028599080756476714,
    "totalApyMonthly": 0.8698887063428334,
    "extraRewards": "[]",
    "isActive": true,
    "rewardsCoin": "JOE"
  },
  {
    "poolNumber": "28",
    "protocolName": "TraderJoe",
    "contract": "0xd6a4F121CA35509aF06A0Be99093d08462f53052",
    "symbol0Name": "WAVAX",
    "symbol1Name": "USDT.e",
    "symbol0address": "0xb31f66aa3c1e785363f0875a1b74e27b85fd66c7",
    "symbol0price": "81.4642480000000000",
    "symbol1address": "0xc7198437980c041c805a1edcba50c1ce5db95118",
    "symbol1price": "0.9965452300000000",
    "network": "avaxc",
    "lpAddress": "0xed8cbd9f0ce3c6986b22002f03c6475ceb7a6256",
    "coinsASec": 0.478125,
    "tvl": 144914000,
    "apy": "12.926238847334",
    "apyDaily": 0.03541435300639452,
    "apyMonthly": 1.0771865706111667,
    "totalApy": 12.926238847334,
    "totalApyDaily": 0.03541435300639452,
    "totalApyMonthly": 1.0771865706111667,
    "extraRewards": "[]",
    "isActive": true,
    "rewardsCoin": "JOE"
  },
  {
    "poolNumber": "26",
    "protocolName": "TraderJoe",
    "contract": "0xd6a4F121CA35509aF06A0Be99093d08462f53052",
    "symbol0Name": "WETH.e",
    "symbol1Name": "WAVAX",
    "symbol0address": "0x49d5c2bdffac6ce2bfdb6640f4f80f226bc10bab",
    "symbol0price": "2921.4322280000000000",
    "symbol1address": "0xb31f66aa3c1e785363f0875a1b74e27b85fd66c7",
    "symbol1price": "81.4642480000000000",
    "network": "avaxc",
    "lpAddress": "0xfe15c2695f1f920da45c30aae47d11de51007af9",
    "coinsASec": 0.31875,
    "tvl": 118177000,
    "apy": "10.56719040731",
    "apyDaily": 0.02895120659536986,
    "apyMonthly": 0.8805992006091666,
    "totalApy": 10.56719040731,
    "totalApyDaily": 0.02895120659536986,
    "totalApyMonthly": 0.8805992006091666,
    "extraRewards": "[]",
    "isActive": true,
    "rewardsCoin": "JOE"
  },
  {
    "poolNumber": "24",
    "protocolName": "TraderJoe",
    "contract": "0xd6a4F121CA35509aF06A0Be99093d08462f53052",
    "symbol0Name": "xJOE",
    "symbol1Name": "",
    "symbol0address": "0x57319d41f71e81f3c65f2a47ca4e001ebafd4f33",
    "symbol0price": "1.6046357582536000",
    "symbol1address": "",
    "symbol1price": 0,
    "network": "avaxc",
    "lpAddress": "0x57319d41f71e81f3c65f2a47ca4e001ebafd4f33",
    "coinsASec": 0.31875,
    "tvl": 77082300,
    "apy": "16.200847606043",
    "apyDaily": 0.0443858838521726,
    "apyMonthly": 1.3500706338369166,
    "totalApy": 16.200847606043,
    "totalApyDaily": 0.0443858838521726,
    "totalApyMonthly": 1.3500706338369166,
    "extraRewards": "[]",
    "isActive": true,
    "rewardsCoin": "JOE"
  },
  {
    "poolNumber": "29",
    "protocolName": "TraderJoeV3",
    "contract": "0x188bED1968b795d5c9022F6a0bb5931Ac4c18F00",
    "symbol0Name": "USDC.e",
    "symbol1Name": "USDC",
    "symbol0address": "0xa7d7079b0fead91f3e65f86e8915cb59c1a4c664",
    "symbol0price": "1.0000000000000000",
    "symbol1address": "0xb97ef9ef8734c71904d8002f8b6bc66dd9c48a6e",
    "symbol1price": "0.9980370000000000",
    "network": "avaxc",
    "lpAddress": "0x2a8a315e82f85d1f0658c5d66a452bbdd9356783",
    "coinsASec": 0.0104518,
    "tvl": 49503600,
    "apy": "0.82717097146596",
    "apyDaily": 0.002266221839632767,
    "apyMonthly": 0.06893091428883,
    "totalApy": 0.82717097146596,
    "totalApyDaily": 0.002266221839632767,
    "totalApyMonthly": 0.06893091428883,
    "extraRewards": "[]",
    "isActive": true,
    "rewardsCoin": "JOE"
  },
  {
    "poolNumber": "0",
    "protocolName": "TraderJoeV3",
    "contract": "0x188bED1968b795d5c9022F6a0bb5931Ac4c18F00",
    "symbol0Name": "JOE",
    "symbol1Name": "WAVAX",
    "symbol0address": "0x6e84a6216ea6dacc71ee8e6b0a5b7322eebc0fdd",
    "symbol0price": "1.2402320000000000",
    "symbol1address": "0xb31f66aa3c1e785363f0875a1b74e27b85fd66c7",
    "symbol1price": "81.4642480000000000",
    "network": "avaxc",
    "lpAddress": "0x454e67025631c065d3cfad6d71e6892f74487a15",
    "coinsASec": 0.470329,
    "tvl": 41413200,
    "apy": "44.494429736997",
    "apyDaily": 0.12190254722464931,
    "apyMonthly": 3.70786914474975,
    "totalApy": 44.494429736997,
    "totalApyDaily": 0.12190254722464931,
    "totalApyMonthly": 3.70786914474975,
    "extraRewards": "[{\"coinAddress\":\"0xb31f66aa3c1e785363f0875a1b74e27b85fd66c7\",\"rewarderASec\":0,\"rewarderASecUSDT\":0,\"Apy\":0}]",
    "isActive": true,
    "rewardsCoin": "JOE"
  },
  {
    "poolNumber": "27",
    "protocolName": "TraderJoe",
    "contract": "0xd6a4F121CA35509aF06A0Be99093d08462f53052",
    "symbol0Name": "WBTC.e",
    "symbol1Name": "WAVAX",
    "symbol0address": "0x50b7545627a5162f82a992c33b87adc75187b218",
    "symbol0price": "41908.5428880000000000",
    "symbol1address": "0xb31f66aa3c1e785363f0875a1b74e27b85fd66c7",
    "symbol1price": "81.4642480000000000",
    "network": "avaxc",
    "lpAddress": "0xd5a37dc5c9a396a03dd1136fc76a1a02b1c88ffa",
    "coinsASec": 0.085,
    "tvl": 33691100,
    "apy": "9.8842990227211",
    "apyDaily": 0.0270802712951263,
    "apyMonthly": 0.8236915852267583,
    "totalApy": 9.8842990227211,
    "totalApyDaily": 0.0270802712951263,
    "totalApyMonthly": 0.8236915852267583,
    "extraRewards": "[]",
    "isActive": true,
    "rewardsCoin": "JOE"
  },
  {
    "poolNumber": "43",
    "protocolName": "TraderJoe",
    "contract": "0xd6a4F121CA35509aF06A0Be99093d08462f53052",
    "symbol0Name": "MIM",
    "symbol1Name": "WAVAX",
    "symbol0address": "0x130966628846bfd36ff31a822705796e8cb8c18d",
    "symbol0price": "0.7821540000000000",
    "symbol1address": "0xb31f66aa3c1e785363f0875a1b74e27b85fd66c7",
    "symbol1price": "81.4642480000000000",
    "network": "avaxc",
    "lpAddress": "0x781655d802670bba3c89aebaaea59d3182fd755d",
    "coinsASec": 0.1275,
    "tvl": 25797500,
    "apy": "19.363119794409",
    "apyDaily": 0.05304964327235342,
    "apyMonthly": 1.6135933162007499,
    "totalApy": 19.363119794409,
    "totalApyDaily": 0.05304964327235342,
    "totalApyMonthly": 1.6135933162007499,
    "extraRewards": "[]",
    "isActive": true,
    "rewardsCoin": "JOE"
  },
  {
    "poolNumber": "29",
    "protocolName": "TraderJoe",
    "contract": "0xd6a4F121CA35509aF06A0Be99093d08462f53052",
    "symbol0Name": "LINK.e",
    "symbol1Name": "WAVAX",
    "symbol0address": "0x5947bb275c521040051d82396192181b413227a3",
    "symbol0price": "16.1714980000000000",
    "symbol1address": "0xb31f66aa3c1e785363f0875a1b74e27b85fd66c7",
    "symbol1price": "81.4642480000000000",
    "network": "avaxc",
    "lpAddress": "0x6f3a0c89f611ef5dc9d96650324ac633d02265d3",
    "coinsASec": 0.053125,
    "tvl": 17112300,
    "apy": "12.16275043538",
    "apyDaily": 0.03332260393254794,
    "apyMonthly": 1.0135625362816667,
    "totalApy": 12.16275043538,
    "totalApyDaily": 0.03332260393254794,
    "totalApyMonthly": 1.0135625362816667,
    "extraRewards": "[]",
    "isActive": true,
    "rewardsCoin": "JOE"
  },
  {
    "poolNumber": "37",
    "protocolName": "TraderJoe",
    "contract": "0xd6a4F121CA35509aF06A0Be99093d08462f53052",
    "symbol0Name": "WAVAX",
    "symbol1Name": "DAI.e",
    "symbol0address": "0xb31f66aa3c1e785363f0875a1b74e27b85fd66c7",
    "symbol0price": "81.4642480000000000",
    "symbol1address": "0xd586e7f844cea2f87f50152665bcbc2c279d8d70",
    "symbol1price": "0.9955130000000000",
    "network": "avaxc",
    "lpAddress": "0x87dee1cc9ffd464b79e058ba20387c1984aed86a",
    "coinsASec": 0,
    "tvl": 15308100,
    "apy": "0",
    "apyDaily": 0,
    "apyMonthly": 0,
    "totalApy": 0,
    "totalApyDaily": 0,
    "totalApyMonthly": 0,
    "extraRewards": "[]",
    "isActive": true,
    "rewardsCoin": "JOE"
  },
  {
    "poolNumber": "28",
    "protocolName": "TraderJoeV3",
    "contract": "0x188bED1968b795d5c9022F6a0bb5931Ac4c18F00",
    "symbol0Name": "PTP",
    "symbol1Name": "WAVAX",
    "symbol0address": "0x22d4002028f537599be9f666d1c4fa138522f9c8",
    "symbol0price": "3.8329330000000000",
    "symbol1address": "0xb31f66aa3c1e785363f0875a1b74e27b85fd66c7",
    "symbol1price": "81.4642480000000000",
    "network": "avaxc",
    "lpAddress": "0xcdfd91eea657cc2701117fe9711c9a4f61feed23",
    "coinsASec": 0.0104518,
    "tvl": 13308400,
    "apy": "3.0768522619511",
    "apyDaily": 0.008429732224523562,
    "apyMonthly": 0.2564043551625917,
    "totalApy": 213.39036845761,
    "totalApyDaily": 0.5846311464592056,
    "totalApyMonthly": 17.782530704800834,
    "extraRewards": "[{\"coinAddress\":\"0x22d4002028f537599be9f666d1c4fa138522f9c8\",\"rewarderASec\":0.2314814815,\"rewarderASecUSDT\":0.887535648219151,\"Apy\":210.31351619566001}]",
    "isActive": true,
    "rewardsCoin": "JOE"
  },
  {
    "poolNumber": "58",
    "protocolName": "TraderJoe",
    "contract": "0xd6a4F121CA35509aF06A0Be99093d08462f53052",
    "symbol0Name": "JOE",
    "symbol1Name": "USDC.e",
    "symbol0address": "0x6e84a6216ea6dacc71ee8e6b0a5b7322eebc0fdd",
    "symbol0price": "1.2402320000000000",
    "symbol1address": "0xa7d7079b0fead91f3e65f86e8915cb59c1a4c664",
    "symbol1price": "1.0000000000000000",
    "network": "avaxc",
    "lpAddress": "0x67926d973cd8ee876ad210faaf7dffa99e414acf",
    "coinsASec": 0.10625,
    "tvl": 9543170,
    "apy": "43.619285312447",
    "apyDaily": 0.11950489126697808,
    "apyMonthly": 3.6349404427039165,
    "totalApy": 43.619285312447,
    "totalApyDaily": 0.11950489126697808,
    "totalApyMonthly": 3.6349404427039165,
    "extraRewards": "[]",
    "isActive": true,
    "rewardsCoin": "JOE"
  },
  {
    "poolNumber": "52",
    "protocolName": "TraderJoe",
    "contract": "0xd6a4F121CA35509aF06A0Be99093d08462f53052",
    "symbol0Name": "BNB",
    "symbol1Name": "WAVAX",
    "symbol0address": "0x264c1383ea520f73dd837f915ef3a732e204a493",
    "symbol0price": "400.3596390000000000",
    "symbol1address": "0xb31f66aa3c1e785363f0875a1b74e27b85fd66c7",
    "symbol1price": "81.4642480000000000",
    "network": "avaxc",
    "lpAddress": "0xeb8eb6300c53c3addbb7382ff6c6fbc4165b0742",
    "coinsASec": 0.02125,
    "tvl": 7578810,
    "apy": "10.984995524483",
    "apyDaily": 0.030095878149268496,
    "apyMonthly": 0.9154162937069167,
    "totalApy": 10.984995524483,
    "totalApyDaily": 0.030095878149268496,
    "totalApyMonthly": 0.9154162937069167,
    "extraRewards": "[]",
    "isActive": true,
    "rewardsCoin": "JOE"
  },
  {
    "poolNumber": "21",
    "protocolName": "TraderJoeV3",
    "contract": "0x188bED1968b795d5c9022F6a0bb5931Ac4c18F00",
    "symbol0Name": "gOHM",
    "symbol1Name": "WAVAX",
    "symbol0address": "0x321e7092a180bb43555132ec53aaa65a5bf84251",
    "symbol0price": "5718.5369270000000000",
    "symbol1address": "0xb31f66aa3c1e785363f0875a1b74e27b85fd66c7",
    "symbol1price": "81.4642480000000000",
    "network": "avaxc",
    "lpAddress": "0xb674f93952f02f2538214d4572aa47f262e990ff",
    "coinsASec": 0.0418071,
    "tvl": 5703100,
    "apy": "28.719756375737",
    "apyDaily": 0.07868426404311507,
    "apyMonthly": 2.3933130313114166,
    "totalApy": 28.719756375737,
    "totalApyDaily": 0.07868426404311507,
    "totalApyMonthly": 2.3933130313114166,
    "extraRewards": "[{\"coinAddress\":\"0x321e7092a180bb43555132ec53aaa65a5bf84251\",\"rewarderASec\":0,\"rewarderASecUSDT\":0,\"Apy\":0}]",
    "isActive": true,
    "rewardsCoin": "JOE"
  },
  {
    "poolNumber": "55",
    "protocolName": "TraderJoe",
    "contract": "0xd6a4F121CA35509aF06A0Be99093d08462f53052",
    "symbol0Name": "WETH.e",
    "symbol1Name": "USDC.e",
    "symbol0address": "0x49d5c2bdffac6ce2bfdb6640f4f80f226bc10bab",
    "symbol0price": "2921.4322280000000000",
    "symbol1address": "0xa7d7079b0fead91f3e65f86e8915cb59c1a4c664",
    "symbol1price": "1.0000000000000000",
    "network": "avaxc",
    "lpAddress": "0x199fb78019a08af2cb6a078409d0c8233eba8a0c",
    "coinsASec": 0.010625,
    "tvl": 5145670,
    "apy": "8.0896331300784",
    "apyDaily": 0.022163378438570962,
    "apyMonthly": 0.6741360941732001,
    "totalApy": 8.0896331300784,
    "totalApyDaily": 0.022163378438570962,
    "totalApyMonthly": 0.6741360941732001,
    "extraRewards": "[]",
    "isActive": true,
    "rewardsCoin": "JOE"
  },
  {
    "poolNumber": "54",
    "protocolName": "TraderJoe",
    "contract": "0xd6a4F121CA35509aF06A0Be99093d08462f53052",
    "symbol0Name": "WBTC.e",
    "symbol1Name": "USDC.e",
    "symbol0address": "0x50b7545627a5162f82a992c33b87adc75187b218",
    "symbol0price": "41908.5428880000000000",
    "symbol1address": "0xa7d7079b0fead91f3e65f86e8915cb59c1a4c664",
    "symbol1price": "1.0000000000000000",
    "network": "avaxc",
    "lpAddress": "0x62475f52add016a06b398aa3b2c2f2e540d36859",
    "coinsASec": 0.010625,
    "tvl": 5062690,
    "apy": "8.2222264037026",
    "apyDaily": 0.022526647681376983,
    "apyMonthly": 0.6851855336418833,
    "totalApy": 8.2222264037026,
    "totalApyDaily": 0.022526647681376983,
    "totalApyMonthly": 0.6851855336418833,
    "extraRewards": "[]",
    "isActive": true,
    "rewardsCoin": "JOE"
  },
  {
    "poolNumber": "50",
    "protocolName": "TraderJoeV3",
    "contract": "0x188bED1968b795d5c9022F6a0bb5931Ac4c18F00",
    "symbol0Name": "WAVAX",
    "symbol1Name": "USDC",
    "symbol0address": "0xb31f66aa3c1e785363f0875a1b74e27b85fd66c7",
    "symbol0price": "81.4642480000000000",
    "symbol1address": "0xb97ef9ef8734c71904d8002f8b6bc66dd9c48a6e",
    "symbol1price": "0.9980370000000000",
    "network": "avaxc",
    "lpAddress": "0xf4003f4efbe8691b60249e6afbd307abe7758adb",
    "coinsASec": 0.0209035,
    "tvl": 4922080,
    "apy": "16.638466482738",
    "apyDaily": 0.045584839678734244,
    "apyMonthly": 1.3865388735615,
    "totalApy": 16.638466482738,
    "totalApyDaily": 0.045584839678734244,
    "totalApyMonthly": 1.3865388735615,
    "extraRewards": "[]",
    "isActive": true,
    "rewardsCoin": "JOE"
  },
  {
    "poolNumber": "3",
    "protocolName": "TraderJoeV3",
    "contract": "0x188bED1968b795d5c9022F6a0bb5931Ac4c18F00",
    "symbol0Name": "WAVAX",
    "symbol1Name": "SPELL",
    "symbol0address": "0xb31f66aa3c1e785363f0875a1b74e27b85fd66c7",
    "symbol0price": "81.4642480000000000",
    "symbol1address": "0xce1bffbd5374dac86a2893119683f4911a2f7814",
    "symbol1price": "0.0064790000000000",
    "network": "avaxc",
    "lpAddress": "0x62cf16bf2bc053e7102e2ac1dee5029b94008d99",
    "coinsASec": 0.0418071,
    "tvl": 3759220,
    "apy": "43.570697106354",
    "apyDaily": 0.11937177289412054,
    "apyMonthly": 3.6308914255294997,
    "totalApy": 43.570697106354,
    "totalApyDaily": 0.11937177289412054,
    "totalApyMonthly": 3.6308914255294997,
    "extraRewards": "[{\"coinAddress\":\"0xb31f66aa3c1e785363f0875a1b74e27b85fd66c7\",\"rewarderASec\":0,\"rewarderASecUSDT\":0,\"Apy\":0}]",
    "isActive": true,
    "rewardsCoin": "JOE"
  },
  {
    "poolNumber": "56",
    "protocolName": "TraderJoe",
    "contract": "0xd6a4F121CA35509aF06A0Be99093d08462f53052",
    "symbol0Name": "LINK.e",
    "symbol1Name": "USDC.e",
    "symbol0address": "0x5947bb275c521040051d82396192181b413227a3",
    "symbol0price": "16.1714980000000000",
    "symbol1address": "0xa7d7079b0fead91f3e65f86e8915cb59c1a4c664",
    "symbol1price": "1.0000000000000000",
    "network": "avaxc",
    "lpAddress": "0xb9f425bc9af072a91c423e31e9eb7e04f226b39d",
    "coinsASec": 0.010625,
    "tvl": 3644460,
    "apy": "11.421882924694",
    "apyDaily": 0.031292829930668495,
    "apyMonthly": 0.9518235770578333,
    "totalApy": 11.421882924694,
    "totalApyDaily": 0.031292829930668495,
    "totalApyMonthly": 0.9518235770578333,
    "extraRewards": "[]",
    "isActive": true,
    "rewardsCoin": "JOE"
  },
  {
    "poolNumber": "13",
    "protocolName": "TraderJoeV3",
    "contract": "0x188bED1968b795d5c9022F6a0bb5931Ac4c18F00",
    "symbol0Name": "CRA",
    "symbol1Name": "WAVAX",
    "symbol0address": "0xa32608e873f9ddef944b24798db69d80bbb4d1ed",
    "symbol0price": "1.5125550000000000",
    "symbol1address": "0xb31f66aa3c1e785363f0875a1b74e27b85fd66c7",
    "symbol1price": "81.4642480000000000",
    "network": "avaxc",
    "lpAddress": "0x140cac5f0e05cbec857e65353839fddd0d8482c1",
    "coinsASec": 0.0313553,
    "tvl": 3407830,
    "apy": "36.047487680772",
    "apyDaily": 0.09876024022129315,
    "apyMonthly": 3.003957306731,
    "totalApy": 36.047487680772,
    "totalApyDaily": 0.09876024022129315,
    "totalApyMonthly": 3.003957306731,
    "extraRewards": "[{\"coinAddress\":\"0xb31f66aa3c1e785363f0875a1b74e27b85fd66c7\",\"rewarderASec\":0,\"rewarderASecUSDT\":0,\"Apy\":0}]",
    "isActive": true,
    "rewardsCoin": "JOE"
  },
  {
    "poolNumber": "2",
    "protocolName": "TraderJoeV3",
    "contract": "0x188bED1968b795d5c9022F6a0bb5931Ac4c18F00",
    "symbol0Name": "WAVAX",
    "symbol1Name": "XAVA",
    "symbol0address": "0xb31f66aa3c1e785363f0875a1b74e27b85fd66c7",
    "symbol0price": "81.4642480000000000",
    "symbol1address": "0xd1c3f94de7e5b45fa4edbba472491a9f4b166fc4",
    "symbol1price": "5.5204150000000000",
    "network": "avaxc",
    "lpAddress": "0x72c3438cf1c915ecf5d9f17a6ed346b273d5bf71",
    "coinsASec": 0.0418071,
    "tvl": 3284770,
    "apy": "49.863945210327",
    "apyDaily": 0.13661354852144383,
    "apyMonthly": 4.1553287675272506,
    "totalApy": 49.863945210327,
    "totalApyDaily": 0.13661354852144383,
    "totalApyMonthly": 4.1553287675272506,
    "extraRewards": "[{\"coinAddress\":\"0xb31f66aa3c1e785363f0875a1b74e27b85fd66c7\",\"rewarderASec\":0,\"rewarderASecUSDT\":0,\"Apy\":0}]",
    "isActive": true,
    "rewardsCoin": "JOE"
  },
  {
    "poolNumber": "49",
    "protocolName": "TraderJoeV3",
    "contract": "0x188bED1968b795d5c9022F6a0bb5931Ac4c18F00",
    "symbol0Name": "UST",
    "symbol1Name": "USDC.e",
    "symbol0address": "0x260bbf5698121eb85e7a74f2e45e16ce762ebe11",
    "symbol0price": "1.0041540000000000",
    "symbol1address": "0xa7d7079b0fead91f3e65f86e8915cb59c1a4c664",
    "symbol1price": "1.0000000000000000",
    "network": "avaxc",
    "lpAddress": "0xa3a029224857bf467e896523e268a5fc005ce810",
    "coinsASec": 0.0104518,
    "tvl": 2878000,
    "apy": "14.227912633904",
    "apyDaily": 0.03898058255864109,
    "apyMonthly": 1.1856593861586666,
    "totalApy": 14.227912633904,
    "totalApyDaily": 0.03898058255864109,
    "totalApyMonthly": 1.1856593861586666,
    "extraRewards": "[]",
    "isActive": true,
    "rewardsCoin": "JOE"
  },
  {
    "poolNumber": "12",
    "protocolName": "TraderJoeV3",
    "contract": "0x188bED1968b795d5c9022F6a0bb5931Ac4c18F00",
    "symbol0Name": "WAVAX",
    "symbol1Name": "PEFI",
    "symbol0address": "0xb31f66aa3c1e785363f0875a1b74e27b85fd66c7",
    "symbol0price": "81.4642480000000000",
    "symbol1address": "0xe896cdeaac9615145c0ca09c8cd5c25bced6384c",
    "symbol1price": "0.3613360000000000",
    "network": "avaxc",
    "lpAddress": "0xb78c8238bd907c42be45aebdb4a8c8a5d7b49755",
    "coinsASec": 0.0104518,
    "tvl": 2403860,
    "apy": "17.034240544486",
    "apyDaily": 0.04666915217667397,
    "apyMonthly": 1.4195200453738333,
    "totalApy": 17.034240544486,
    "totalApyDaily": 0.04666915217667397,
    "totalApyMonthly": 1.4195200453738333,
    "extraRewards": "[{\"coinAddress\":\"0xb31f66aa3c1e785363f0875a1b74e27b85fd66c7\",\"rewarderASec\":0,\"rewarderASecUSDT\":0,\"Apy\":0}]",
    "isActive": true,
    "rewardsCoin": "JOE"
  },
  {
    "poolNumber": "62",
    "protocolName": "TraderJoe",
    "contract": "0xd6a4F121CA35509aF06A0Be99093d08462f53052",
    "symbol0Name": "AAVE.e",
    "symbol1Name": "WAVAX",
    "symbol0address": "0x63a72806098bd3d9520cc43356dd78afe5d386d9",
    "symbol0price": "161.1070160000000000",
    "symbol1address": "0xb31f66aa3c1e785363f0875a1b74e27b85fd66c7",
    "symbol1price": "81.4642480000000000",
    "network": "avaxc",
    "lpAddress": "0xc3e6d9f7a3a5e3e223356383c7c055ee3f26a34f",
    "coinsASec": 0.010625,
    "tvl": 2213800,
    "apy": "18.803214204367",
    "apyDaily": 0.05151565535443013,
    "apyMonthly": 1.5669345170305833,
    "totalApy": 18.803214204367,
    "totalApyDaily": 0.05151565535443013,
    "totalApyMonthly": 1.5669345170305833,
    "extraRewards": "[]",
    "isActive": true,
    "rewardsCoin": "JOE"
  },
  {
    "poolNumber": "27",
    "protocolName": "TraderJoeV3",
    "contract": "0x188bED1968b795d5c9022F6a0bb5931Ac4c18F00",
    "symbol0Name": "H2O",
    "symbol1Name": "WAVAX",
    "symbol0address": "0x026187bdbc6b751003517bcb30ac7817d5b766f8",
    "symbol0price": "0.9823260000000000",
    "symbol1address": "0xb31f66aa3c1e785363f0875a1b74e27b85fd66c7",
    "symbol1price": "81.4642480000000000",
    "network": "avaxc",
    "lpAddress": "0x9615a11eaa912eae869e9c1097df263fc3e105f3",
    "coinsASec": 0.00541857,
    "tvl": 1853050,
    "apy": "41.452955621662",
    "apyDaily": 0.11356974142921096,
    "apyMonthly": 3.4544129684718334,
    "totalApy": 0,
    "totalApyDaily": 0,
    "totalApyMonthly": 0,
    "extraRewards": "[]",
    "isActive": true,
    "rewardsCoin": "JOE"
  },
  {
    "poolNumber": "19",
    "protocolName": "TraderJoeV3",
    "contract": "0x188bED1968b795d5c9022F6a0bb5931Ac4c18F00",
    "symbol0Name": "MELT",
    "symbol1Name": "WAVAX",
    "symbol0address": "0x47eb6f7525c1aa999fbc9ee92715f5231eb1241d",
    "symbol0price": "2.5486850000000000",
    "symbol1address": "0xb31f66aa3c1e785363f0875a1b74e27b85fd66c7",
    "symbol1price": "81.4642480000000000",
    "network": "avaxc",
    "lpAddress": "0x2923a62b2531ec744ca0c1e61dffab1ad9369feb",
    "coinsASec": 0.00522588,
    "tvl": 1836310,
    "apy": "11.149499100075",
    "apyDaily": 0.030546572876917807,
    "apyMonthly": 0.92912492500625,
    "totalApy": 11.149499100075,
    "totalApyDaily": 0.030546572876917807,
    "totalApyMonthly": 0.92912492500625,
    "extraRewards": "[{\"coinAddress\":\"0x47eb6f7525c1aa999fbc9ee92715f5231eb1241d\",\"rewarderASec\":0,\"rewarderASecUSDT\":0,\"Apy\":0}]",
    "isActive": true,
    "rewardsCoin": "JOE"
  },
  {
    "poolNumber": "40",
    "protocolName": "TraderJoeV3",
    "contract": "0x188bED1968b795d5c9022F6a0bb5931Ac4c18F00",
    "symbol0Name": "DCAU",
    "symbol1Name": "WAVAX",
    "symbol0address": "0x100cc3a819dd3e8573fd2e46d1e66ee866068f30",
    "symbol0price": "128.3712820000000000",
    "symbol1address": "0xb31f66aa3c1e785363f0875a1b74e27b85fd66c7",
    "symbol1price": "81.4642480000000000",
    "network": "avaxc",
    "lpAddress": "0x81034a38a124a3290dc226798f34c6645b153a02",
    "coinsASec": 0.0104518,
    "tvl": 1820970,
    "apy": "22.48687541028",
    "apyDaily": 0.06160787783638356,
    "apyMonthly": 1.87390628419,
    "totalApy": 125.85948496959,
    "totalApyDaily": 0.344820506766,
    "totalApyMonthly": 10.4882904141325,
    "extraRewards": "[{\"coinAddress\":\"0x100cc3a819dd3e8573fd2e46d1e66ee866068f30\",\"rewarderASec\":0.0004625,\"rewarderASecUSDT\":0.0596900071875,\"Apy\":103.3726095593093}]",
    "isActive": true,
    "rewardsCoin": "JOE"
  },
  {
    "poolNumber": "30",
    "protocolName": "TraderJoe",
    "contract": "0xd6a4F121CA35509aF06A0Be99093d08462f53052",
    "symbol0Name": "JOE",
    "symbol1Name": "USDT.e",
    "symbol0address": "0x6e84a6216ea6dacc71ee8e6b0a5b7322eebc0fdd",
    "symbol0price": "1.2402320000000000",
    "symbol1address": "0xc7198437980c041c805a1edcba50c1ce5db95118",
    "symbol1price": "0.9965452300000000",
    "network": "avaxc",
    "lpAddress": "0x1643de2efb8e35374d796297a9f95f64c082a8ce",
    "coinsASec": 0.0337922,
    "tvl": 1761840,
    "apy": "30.86766216929",
    "apyDaily": 0.08456893745010959,
    "apyMonthly": 2.572305180774167,
    "totalApy": 0,
    "totalApyDaily": 0,
    "totalApyMonthly": 0,
    "extraRewards": "[]",
    "isActive": true,
    "rewardsCoin": "JOE"
  },
  {
    "poolNumber": "47",
    "protocolName": "TraderJoeV3",
    "contract": "0x188bED1968b795d5c9022F6a0bb5931Ac4c18F00",
    "symbol0Name": "WAVAX",
    "symbol1Name": "DOMI",
    "symbol0address": "0xb31f66aa3c1e785363f0875a1b74e27b85fd66c7",
    "symbol0price": "81.4642480000000000",
    "symbol1address": "0xfc6da929c031162841370af240dec19099861d3b",
    "symbol1price": "0.2325550000000000",
    "network": "avaxc",
    "lpAddress": "0x5b9faf0fea95df4d4cb894ef920704daff656f3e",
    "coinsASec": 0.0104518,
    "tvl": 1595650,
    "apy": "25.662273011682",
    "apyDaily": 0.07030759729227945,
    "apyMonthly": 2.1385227509735,
    "totalApy": 380.30457457104,
    "totalApyDaily": 1.0419303412905205,
    "totalApyMonthly": 31.69204788092,
    "extraRewards": "[{\"coinAddress\":\"0xfc6da929c031162841370af240dec19099861d3b\",\"rewarderASec\":0.77160494,\"rewarderASecUSDT\":0.17944058682170003,\"Apy\":354.64230155935945}]",
    "isActive": true,
    "rewardsCoin": "JOE"
  },
  {
    "poolNumber": "44",
    "protocolName": "TraderJoeV3",
    "contract": "0x188bED1968b795d5c9022F6a0bb5931Ac4c18F00",
    "symbol0Name": "WAVAX",
    "symbol1Name": "MORE",
    "symbol0address": "0xb31f66aa3c1e785363f0875a1b74e27b85fd66c7",
    "symbol0price": "81.4642480000000000",
    "symbol1address": "0xd9d90f882cddd6063959a9d837b05cb748718a05",
    "symbol1price": "0.1203180000000000",
    "network": "avaxc",
    "lpAddress": "0xb8361d0e3f3b0fc5e6071f3a3c3271223c49e3d9",
    "coinsASec": 0.0104518,
    "tvl": 1487980,
    "apy": "27.519057257389",
    "apyDaily": 0.07539467741750411,
    "apyMonthly": 2.2932547714490834,
    "totalApy": 224.00953996762,
    "totalApyDaily": 0.6137247670345753,
    "totalApyMonthly": 18.667461663968332,
    "extraRewards": "[{\"coinAddress\":\"0xd9d90f882cddd6063959a9d837b05cb748718a05\",\"rewarderASec\":0.77160494,\"rewarderASecUSDT\":0.09271141996076,\"Apy\":196.49048271023366}]",
    "isActive": true,
    "rewardsCoin": "JOE"
  },
  {
    "poolNumber": "41",
    "protocolName": "TraderJoeV3",
    "contract": "0x188bED1968b795d5c9022F6a0bb5931Ac4c18F00",
    "symbol0Name": "WAVAX",
    "symbol1Name": "HeC",
    "symbol0address": "0xb31f66aa3c1e785363f0875a1b74e27b85fd66c7",
    "symbol0price": "81.4642480000000000",
    "symbol1address": "0xc7f4debc8072e23fe9259a5c0398326d8efb7f5c",
    "symbol1price": "2.4209830000000000",
    "network": "avaxc",
    "lpAddress": "0x4dc5291cdc7ad03342994e35d0ccc76de065a566",
    "coinsASec": 0.0104518,
    "tvl": 1346140,
    "apy": "30.418856873412",
    "apyDaily": 0.08333933389975891,
    "apyMonthly": 2.534904739451,
    "totalApy": 30.418856873412,
    "totalApyDaily": 0.08333933389975891,
    "totalApyMonthly": 2.534904739451,
    "extraRewards": "[{\"coinAddress\":\"0xc7f4debc8072e23fe9259a5c0398326d8efb7f5c\",\"rewarderASec\":0,\"rewarderASecUSDT\":0,\"Apy\":0}]",
    "isActive": true,
    "rewardsCoin": "JOE"
  },
  {
    "poolNumber": "22",
    "protocolName": "TraderJoeV3",
    "contract": "0x188bED1968b795d5c9022F6a0bb5931Ac4c18F00",
    "symbol0Name": "aWOOL",
    "symbol1Name": "WAVAX",
    "symbol0address": "0x5ede350e84223fb50775fd91a723f2ca71034cf7",
    "symbol0price": "0.0408690000000000",
    "symbol1address": "0xb31f66aa3c1e785363f0875a1b74e27b85fd66c7",
    "symbol1price": "81.4642480000000000",
    "network": "avaxc",
    "lpAddress": "0xf895e6588585912e60b0131fa173e986859f69d5",
    "coinsASec": 0.00570342,
    "tvl": 1278140,
    "apy": "3.9094483335048",
    "apyDaily": 0.010710817352067945,
    "apyMonthly": 0.3257873611254,
    "totalApy": 0,
    "totalApyDaily": 0,
    "totalApyMonthly": 0,
    "extraRewards": "[]",
    "isActive": true,
    "rewardsCoin": "JOE"
  },
  {
    "poolNumber": "30",
    "protocolName": "TraderJoeV3",
    "contract": "0x188bED1968b795d5c9022F6a0bb5931Ac4c18F00",
    "symbol0Name": "WAVAX",
    "symbol1Name": "IME",
    "symbol0address": "0xb31f66aa3c1e785363f0875a1b74e27b85fd66c7",
    "symbol0price": "81.4642480000000000",
    "symbol1address": "0xf891214fdcf9cdaa5fdc42369ee4f27f226adad6",
    "symbol1price": "0.0416820000000000",
    "network": "avaxc",
    "lpAddress": "0x5d95ae932d42e53bb9da4de65e9b7263a4fa8564",
    "coinsASec": 0.0104518,
    "tvl": 1136180,
    "apy": "36.040060111289",
    "apyDaily": 0.09873989071586028,
    "apyMonthly": 3.003338342607417,
    "totalApy": 36.040060111289,
    "totalApyDaily": 0.09873989071586028,
    "totalApyMonthly": 3.003338342607417,
    "extraRewards": "[{\"coinAddress\":\"0xf891214fdcf9cdaa5fdc42369ee4f27f226adad6\",\"rewarderASec\":0,\"rewarderASecUSDT\":0,\"Apy\":0}]",
    "isActive": true,
    "rewardsCoin": "JOE"
  },
  {
    "poolNumber": "0",
    "protocolName": "TraderJoe",
    "contract": "0xd6a4F121CA35509aF06A0Be99093d08462f53052",
    "symbol0Name": "JOE",
    "symbol1Name": "WAVAX",
    "symbol0address": "0x6e84a6216ea6dacc71ee8e6b0a5b7322eebc0fdd",
    "symbol0price": "1.2402320000000000",
    "symbol1address": "0xb31f66aa3c1e785363f0875a1b74e27b85fd66c7",
    "symbol1price": "81.4642480000000000",
    "network": "avaxc",
    "lpAddress": "0x454e67025631c065d3cfad6d71e6892f74487a15",
    "coinsASec": 0,
    "tvl": 1051580,
    "apy": "0",
    "apyDaily": 0,
    "apyMonthly": 0,
    "totalApy": 0,
    "totalApyDaily": 0,
    "totalApyMonthly": 0,
    "extraRewards": "[]",
    "isActive": true,
    "rewardsCoin": "JOE"
  },
  {
    "poolNumber": "1",
    "protocolName": "TraderJoeV3",
    "contract": "0x188bED1968b795d5c9022F6a0bb5931Ac4c18F00",
    "symbol0Name": "YAK",
    "symbol1Name": "WAVAX",
    "symbol0address": "0x59414b3089ce2af0010e7523dea7e2b35d776ec7",
    "symbol0price": "2351.1742400000000000",
    "symbol1address": "0xb31f66aa3c1e785363f0875a1b74e27b85fd66c7",
    "symbol1price": "81.4642480000000000",
    "network": "avaxc",
    "lpAddress": "0xb5c9e891af3063004a441ba4fab4ca3d6deb5626",
    "coinsASec": 0.0104518,
    "tvl": 983983,
    "apy": "41.61444809557",
    "apyDaily": 0.11401218656320547,
    "apyMonthly": 3.467870674630833,
    "totalApy": 41.61444809557,
    "totalApyDaily": 0.11401218656320547,
    "totalApyMonthly": 3.467870674630833,
    "extraRewards": "[{\"coinAddress\":\"0xb31f66aa3c1e785363f0875a1b74e27b85fd66c7\",\"rewarderASec\":0,\"rewarderASecUSDT\":0,\"Apy\":0}]",
    "isActive": true,
    "rewardsCoin": "JOE"
  },
  {
    "poolNumber": "11",
    "protocolName": "TraderJoeV3",
    "contract": "0x188bED1968b795d5c9022F6a0bb5931Ac4c18F00",
    "symbol0Name": "WAVAX",
    "symbol1Name": "SNOB",
    "symbol0address": "0xb31f66aa3c1e785363f0875a1b74e27b85fd66c7",
    "symbol0price": "81.4642480000000000",
    "symbol1address": "0xc38f41a296a4493ff429f1238e030924a1542e50",
    "symbol1price": "0.2853890000000000",
    "network": "avaxc",
    "lpAddress": "0x8fb5bd3ac8efd05dacae82f512dd03e14aadab73",
    "coinsASec": 0.0104518,
    "tvl": 827059,
    "apy": "49.510304473578",
    "apyDaily": 0.13564466979062467,
    "apyMonthly": 4.1258587061315,
    "totalApy": 49.510304473578,
    "totalApyDaily": 0.13564466979062467,
    "totalApyMonthly": 4.1258587061315,
    "extraRewards": "[{\"coinAddress\":\"0xb31f66aa3c1e785363f0875a1b74e27b85fd66c7\",\"rewarderASec\":0,\"rewarderASecUSDT\":0,\"Apy\":0}]",
    "isActive": true,
    "rewardsCoin": "JOE"
  },
  {
    "poolNumber": "20",
    "protocolName": "TraderJoeV3",
    "contract": "0x188bED1968b795d5c9022F6a0bb5931Ac4c18F00",
    "symbol0Name": "CRAFT",
    "symbol1Name": "WAVAX",
    "symbol0address": "0x8ae8be25c23833e0a01aa200403e826f611f9cd2",
    "symbol0price": "0.5577080000000000",
    "symbol1address": "0xb31f66aa3c1e785363f0875a1b74e27b85fd66c7",
    "symbol1price": "81.4642480000000000",
    "network": "avaxc",
    "lpAddress": "0x86d1b1ab4812a104bc1ea1fbd07809de636e6c6b",
    "coinsASec": 0.0209035,
    "tvl": 715604,
    "apy": "114.44302851567",
    "apyDaily": 0.3135425438785479,
    "apyMonthly": 9.5369190429725,
    "totalApy": 114.44302851567,
    "totalApyDaily": 0.3135425438785479,
    "totalApyMonthly": 9.5369190429725,
    "extraRewards": "[{\"coinAddress\":\"0x8ae8be25c23833e0a01aa200403e826f611f9cd2\",\"rewarderASec\":0,\"rewarderASecUSDT\":0,\"Apy\":0}]",
    "isActive": true,
    "rewardsCoin": "JOE"
  },
  {
    "poolNumber": "41",
    "protocolName": "TraderJoe",
    "contract": "0xd6a4F121CA35509aF06A0Be99093d08462f53052",
    "symbol0Name": "QI",
    "symbol1Name": "WAVAX",
    "symbol0address": "0x8729438eb15e2c8b576fcc6aecda6a148776c0f5",
    "symbol0price": "0.0507070000000000",
    "symbol1address": "0xb31f66aa3c1e785363f0875a1b74e27b85fd66c7",
    "symbol1price": "81.4642480000000000",
    "network": "avaxc",
    "lpAddress": "0x2774516897ac629ad3ed9dcac7e375dda78412b9",
    "coinsASec": 0.010625,
    "tvl": 622591,
    "apy": "66.860256028591",
    "apyDaily": 0.18317878363997533,
    "apyMonthly": 5.571688002382583,
    "totalApy": 66.860256028591,
    "totalApyDaily": 0.18317878363997533,
    "totalApyMonthly": 5.571688002382583,
    "extraRewards": "[]",
    "isActive": true,
    "rewardsCoin": "JOE"
  },
  {
    "poolNumber": "32",
    "protocolName": "TraderJoeV3",
    "contract": "0x188bED1968b795d5c9022F6a0bb5931Ac4c18F00",
    "symbol0Name": "EGG",
    "symbol1Name": "WAVAX",
    "symbol0address": "0x7761e2338b35bceb6bda6ce477ef012bde7ae611",
    "symbol0price": "1.5936900000000000",
    "symbol1address": "0xb31f66aa3c1e785363f0875a1b74e27b85fd66c7",
    "symbol1price": "81.4642480000000000",
    "network": "avaxc",
    "lpAddress": "0x3052a75dfd7a9d9b0f81e510e01d3fe80a9e7ec7",
    "coinsASec": 0.0104518,
    "tvl": 593977,
    "apy": "68.938589267748",
    "apyDaily": 0.18887284730889864,
    "apyMonthly": 5.744882438979,
    "totalApy": 324.77401418029,
    "totalApyDaily": 0.8897918196720275,
    "totalApyMonthly": 27.064501181690833,
    "extraRewards": "[{\"coinAddress\":\"0xab592d197acc575d16c3346f4eb70c703f308d1e\",\"rewarderASec\":9.921,\"rewarderASecUSDT\":0.048186296999999996,\"Apy\":255.83542491253866}]",
    "isActive": true,
    "rewardsCoin": "JOE"
  },
  {
    "poolNumber": "10",
    "protocolName": "TraderJoeV3",
    "contract": "0x188bED1968b795d5c9022F6a0bb5931Ac4c18F00",
    "symbol0Name": "MAI",
    "symbol1Name": "WAVAX",
    "symbol0address": "0x5c49b268c9841aff1cc3b0a418ff5c3442ee3f3b",
    "symbol0price": "0.9835070000000000",
    "symbol1address": "0xb31f66aa3c1e785363f0875a1b74e27b85fd66c7",
    "symbol1price": "81.4642480000000000",
    "network": "avaxc",
    "lpAddress": "0x23ddca8de11eccd8000263f008a92e10dc1f21e8",
    "coinsASec": 0.00522588,
    "tvl": 563466,
    "apy": "36.335763262309",
    "apyDaily": 0.09955003633509316,
    "apyMonthly": 3.0279802718590836,
    "totalApy": 36.335763262309,
    "totalApyDaily": 0.09955003633509316,
    "totalApyMonthly": 3.0279802718590836,
    "extraRewards": "[]",
    "isActive": true,
    "rewardsCoin": "JOE"
  },
  {
    "poolNumber": "48",
    "protocolName": "TraderJoeV3",
    "contract": "0x188bED1968b795d5c9022F6a0bb5931Ac4c18F00",
    "symbol0Name": "WAVAX",
    "symbol1Name": "TUS",
    "symbol0address": "0xb31f66aa3c1e785363f0875a1b74e27b85fd66c7",
    "symbol0price": "81.4642480000000000",
    "symbol1address": "0xf693248f96fe03422fea95ac0afbbbc4a8fdd172",
    "symbol1price": "0.2248280000000000",
    "network": "avaxc",
    "lpAddress": "0x565d20bd591b00ead0c927e4b6d7dd8a33b0b319",
    "coinsASec": 0.0104518,
    "tvl": 544466,
    "apy": "75.207442418726",
    "apyDaily": 0.2060477874485644,
    "apyMonthly": 6.267286868227167,
    "totalApy": 75.207442418726,
    "totalApyDaily": 0.2060477874485644,
    "totalApyMonthly": 6.267286868227167,
    "extraRewards": "[]",
    "isActive": true,
    "rewardsCoin": "JOE"
  },
  {
    "poolNumber": "24",
    "protocolName": "TraderJoeV3",
    "contract": "0x188bED1968b795d5c9022F6a0bb5931Ac4c18F00",
    "symbol0Name": "KLO",
    "symbol1Name": "WAVAX",
    "symbol0address": "0xb27c8941a7df8958a1778c0259f76d1f8b711c35",
    "symbol0price": "0.2455780000000000",
    "symbol1address": "0xb31f66aa3c1e785363f0875a1b74e27b85fd66c7",
    "symbol1price": "81.4642480000000000",
    "network": "avaxc",
    "lpAddress": "0xb2ff0817ad078c92c3afb82326592e06c92581b8",
    "coinsASec": 0.0104518,
    "tvl": 536529,
    "apy": "76.320008482973",
    "apyDaily": 0.2090959136519808,
    "apyMonthly": 6.360000706914416,
    "totalApy": 76.320008482973,
    "totalApyDaily": 0.2090959136519808,
    "totalApyMonthly": 6.360000706914416,
    "extraRewards": "[{\"coinAddress\":\"0xb27c8941a7df8958a1778c0259f76d1f8b711c35\",\"rewarderASec\":0,\"rewarderASecUSDT\":0,\"Apy\":0}]",
    "isActive": true,
    "rewardsCoin": "JOE"
  },
  {
    "poolNumber": "37",
    "protocolName": "TraderJoeV3",
    "contract": "0x188bED1968b795d5c9022F6a0bb5931Ac4c18F00",
    "symbol0Name": "COOK",
    "symbol1Name": "WAVAX",
    "symbol0address": "0x637afeff75ca669ff92e4570b14d6399a658902f",
    "symbol0price": "0.0037470000000000",
    "symbol1address": "0xb31f66aa3c1e785363f0875a1b74e27b85fd66c7",
    "symbol1price": "81.4642480000000000",
    "network": "avaxc",
    "lpAddress": "0x3fcd1d5450e63fa6af495a601e6ea1230f01c4e3",
    "coinsASec": 0.0104518,
    "tvl": 523138,
    "apy": "78.273591576889",
    "apyDaily": 0.21444819610106577,
    "apyMonthly": 6.522799298074084,
    "totalApy": 240.90566028708,
    "totalApyDaily": 0.6600155076358356,
    "totalApyMonthly": 20.07547169059,
    "extraRewards": "[{\"coinAddress\":\"0x637afeff75ca669ff92e4570b14d6399a658902f\",\"rewarderASec\":7.2,\"rewarderASecUSDT\":0.0269784,\"Apy\":162.63206871019253}]",
    "isActive": true,
    "rewardsCoin": "JOE"
  },
  {
    "poolNumber": "49",
    "protocolName": "TraderJoe",
    "contract": "0xd6a4F121CA35509aF06A0Be99093d08462f53052",
    "symbol0Name": "USDC.e",
    "symbol1Name": "USDT.e",
    "symbol0address": "0xa7d7079b0fead91f3e65f86e8915cb59c1a4c664",
    "symbol0price": "1.0000000000000000",
    "symbol1address": "0xc7198437980c041c805a1edcba50c1ce5db95118",
    "symbol1price": "0.9965452300000000",
    "network": "avaxc",
    "lpAddress": "0x2e02539203256c83c7a9f6fa6f8608a32a2b1ca2",
    "coinsASec": 0,
    "tvl": 503827,
    "apy": "0",
    "apyDaily": 0,
    "apyMonthly": 0,
    "totalApy": 0,
    "totalApyDaily": 0,
    "totalApyMonthly": 0,
    "extraRewards": "[]",
    "isActive": true,
    "rewardsCoin": "JOE"
  },
  {
    "poolNumber": "25",
    "protocolName": "TraderJoeV3",
    "contract": "0x188bED1968b795d5c9022F6a0bb5931Ac4c18F00",
    "symbol0Name": "WAVAX",
    "symbol1Name": "CLY",
    "symbol0address": "0xb31f66aa3c1e785363f0875a1b74e27b85fd66c7",
    "symbol0price": "81.4642480000000000",
    "symbol1address": "0xec3492a2508ddf4fdc0cd76f31f340b30d1793e6",
    "symbol1price": "0.8064820000000000",
    "network": "avaxc",
    "lpAddress": "0x0b2777b0c55aeaaeb56e86b6eefa6cc2cfa00e07",
    "coinsASec": 0.0104518,
    "tvl": 497832,
    "apy": "82.252559546143",
    "apyDaily": 0.22534947820861098,
    "apyMonthly": 6.854379962178584,
    "totalApy": 82.252559546143,
    "totalApyDaily": 0.22534947820861098,
    "totalApyMonthly": 6.854379962178584,
    "extraRewards": "[{\"coinAddress\":\"0xec3492a2508ddf4fdc0cd76f31f340b30d1793e6\",\"rewarderASec\":0,\"rewarderASecUSDT\":0,\"Apy\":0}]",
    "isActive": true,
    "rewardsCoin": "JOE"
  },
  {
    "poolNumber": "44",
    "protocolName": "TraderJoe",
    "contract": "0xd6a4F121CA35509aF06A0Be99093d08462f53052",
    "symbol0Name": "SYN",
    "symbol1Name": "WAVAX",
    "symbol0address": "0x1f1e7c893855525b303f99bdf5c3c05be09ca251",
    "symbol0price": "2.4448330000000000",
    "symbol1address": "0xb31f66aa3c1e785363f0875a1b74e27b85fd66c7",
    "symbol1price": "81.4642480000000000",
    "network": "avaxc",
    "lpAddress": "0x20abdc20758990b6afc90da2f2d30cd0aa3f73c6",
    "coinsASec": 0,
    "tvl": 471130,
    "apy": "0",
    "apyDaily": 0,
    "apyMonthly": 0,
    "totalApy": 0,
    "totalApyDaily": 0,
    "totalApyMonthly": 0,
    "extraRewards": "[]",
    "isActive": true,
    "rewardsCoin": "JOE"
  },
  {
    "poolNumber": "38",
    "protocolName": "TraderJoeV3",
    "contract": "0x188bED1968b795d5c9022F6a0bb5931Ac4c18F00",
    "symbol0Name": "FXS",
    "symbol1Name": "WAVAX",
    "symbol0address": "0x214db107654ff987ad859f34125307783fc8e387",
    "symbol0price": "25.1685690000000000",
    "symbol1address": "0xb31f66aa3c1e785363f0875a1b74e27b85fd66c7",
    "symbol1price": "81.4642480000000000",
    "network": "avaxc",
    "lpAddress": "0x53942dcce5087f56cf1d68f4e017ca3a793f59a2",
    "coinsASec": 0.010625,
    "tvl": 470766,
    "apy": "55.965956989575",
    "apyDaily": 0.15333138901253424,
    "apyMonthly": 4.66382974913125,
    "totalApy": 0,
    "totalApyDaily": 0,
    "totalApyMonthly": 0,
    "extraRewards": "[]",
    "isActive": true,
    "rewardsCoin": "JOE"
  },
  {
    "poolNumber": "36",
    "protocolName": "TraderJoeV3",
    "contract": "0x188bED1968b795d5c9022F6a0bb5931Ac4c18F00",
    "symbol0Name": "ISA",
    "symbol1Name": "WAVAX",
    "symbol0address": "0x3eefb18003d033661f84e48360ebecd181a84709",
    "symbol0price": "0.0020420000000000",
    "symbol1address": "0xb31f66aa3c1e785363f0875a1b74e27b85fd66c7",
    "symbol1price": "81.4642480000000000",
    "network": "avaxc",
    "lpAddress": "0x9155f441ffdfa81b13e385bfac6b3825c05184ee",
    "coinsASec": 0.0104518,
    "tvl": 423980,
    "apy": "96.579933673066",
    "apyDaily": 0.2646025580084,
    "apyMonthly": 8.048327806088833,
    "totalApy": 96.579933673066,
    "totalApyDaily": 0.2646025580084,
    "totalApyMonthly": 8.048327806088833,
    "extraRewards": "[{\"coinAddress\":\"0x3eefb18003d033661f84e48360ebecd181a84709\",\"rewarderASec\":0,\"rewarderASecUSDT\":0,\"Apy\":0}]",
    "isActive": true,
    "rewardsCoin": "JOE"
  },
  {
    "poolNumber": "18",
    "protocolName": "TraderJoeV3",
    "contract": "0x188bED1968b795d5c9022F6a0bb5931Ac4c18F00",
    "symbol0Name": "GRO",
    "symbol1Name": "WAVAX",
    "symbol0address": "0x72699ba15cc734f8db874fa9652c8de12093f187",
    "symbol0price": "15.2064780000000000",
    "symbol1address": "0xb31f66aa3c1e785363f0875a1b74e27b85fd66c7",
    "symbol1price": "81.4642480000000000",
    "network": "avaxc",
    "lpAddress": "0xb7a4ca0c9b58a33b244c44a8bf9833b0e7918429",
    "coinsASec": 0.00522588,
    "tvl": 400760,
    "apy": "51.087805488566",
    "apyDaily": 0.13996659037963288,
    "apyMonthly": 4.257317124047167,
    "totalApy": 298.05733204329,
    "totalApyDaily": 0.816595430255589,
    "totalApyMonthly": 24.838111003607498,
    "extraRewards": "[{\"coinAddress\":\"0xb31f66aa3c1e785363f0875a1b74e27b85fd66c7\",\"rewarderASec\":0.0003858024691,\"rewarderASecUSDT\":0.031384946370544266,\"Apy\":246.96952655472373}]",
    "isActive": true,
    "rewardsCoin": "JOE"
  },
  {
    "poolNumber": "15",
    "protocolName": "TraderJoeV3",
    "contract": "0x188bED1968b795d5c9022F6a0bb5931Ac4c18F00",
    "symbol0Name": "WAVAX",
    "symbol1Name": "BOO",
    "symbol0address": "0xb31f66aa3c1e785363f0875a1b74e27b85fd66c7",
    "symbol0price": "81.4642480000000000",
    "symbol1address": "0xbd83010eb60f12112908774998f65761cf9f6f9a",
    "symbol1price": "19.7464880000000000",
    "network": "avaxc",
    "lpAddress": "0xebf50b8089a0c5e7c5de23f644fcd723818f65b3",
    "coinsASec": 0.00522588,
    "tvl": 362551,
    "apy": "56.471975448202",
    "apyDaily": 0.15471774095397808,
    "apyMonthly": 4.7059979540168335,
    "totalApy": 56.471975448202,
    "totalApyDaily": 0.15471774095397808,
    "totalApyMonthly": 4.7059979540168335,
    "extraRewards": "[]",
    "isActive": true,
    "rewardsCoin": "JOE"
  }
]